full_adder_4bit.v
`timescale 1ps/1ps
module full_adder_4bit (
    input wire[3:0] A,
    input wire[3:0] B,
    input wire Cin,
    output wire[3:0] S,
    output wire Cout
);
    assign {Cout, S} = A + B + Cin;
endmodule

tb_full_adder.v
module tb_full_adder();
    
    initial begin
        $dumpfile("tb_full_adder.vcd");
        $dumpvars(0, full_adder_4bit);
    end
    reg [3:0] A;
    reg [3:0] B;
    reg Cin;
    wire [3:0] S;
    wire Cout;
    full_adder_4bit full_adder_4bit (.A(A), .B(B), .Cin(Cin), .S(S), .Cout(Cout));
    initial begin
        A = 4'b0000; B = 4'b0000; Cin = 0;
        #10 A = 4'b0001; B = 4'b0001; Cin = 0;
        #10 A = 4'b0010; B = 4'b0010; Cin = 0;
        #10 A = 4'b0011; B = 4'b0011; Cin = 0;
        #10 A = 4'b0100; B = 4'b0100; Cin = 0;
        #10 A = 4'b0101; B = 4'b0101; Cin = 0;
        #10 A = 4'b0110; B = 4'b0110; Cin = 0;
        #10 A = 4'b0111; B = 4'b0111; Cin = 0;
        #10 A = 4'b1000; B = 4'b1000; Cin = 0;
        #10 A = 4'b1001; B = 4'b1001; Cin = 0;
        #10 A = 4'b1010; B = 4'b1010; Cin = 0;
        #10 A = 4'b1011; B = 4'b1011; Cin = 0;
        #10 A = 4'b1100; B = 4'b1100; Cin = 0;
        #10 A = 4'b1101; B = 4'b1101; Cin = 0;
        #10 A = 4'b1110; B = 4'b1110; Cin = 0;
        #10 A = 4'b1111; B = 4'b1111;   Cin = 0;
        #10 A = 4'b1111; B = 4'b1111;   Cin = 1;
    end
    
endmodule

tb_full_adder.vcd
$date
	Mon Sep  8 22:27:49 2025
$end
$version
	Icarus Verilog
$end
$timescale
	1ps
$end
$scope module tb_full_adder $end
$scope module full_adder_4bit $end
$var wire 4 ! A [3:0] $end
$var wire 4 " B [3:0] $end
$var wire 1 # Cin $end
$var wire 4 $ S [3:0] $end
$var wire 1 % Cout $end
$upscope $end
$upscope $end
$enddefinitions $end
$comment Show the parameter values. $end
$dumpall
$end
#0
$dumpvars
0%
b0 $
0#
b0 "
b0 !
$end
#10000000000000
b10 $
b1 "
b1 !
#20000000000000
b100 $
b10 "
b10 !
#30000000000000
b110 $
b11 "
b11 !
#40000000000000
b1000 $
b100 "
b100 !
#50000000000000
b1010 $
b101 "
b101 !
#60000000000000
b1100 $
b110 "
b110 !
#70000000000000
b1110 $
b111 "
b111 !
#80000000000000
1%
b0 $
b1000 "
b1000 !
#90000000000000
b10 $
b1001 "
b1001 !
#100000000000000
b100 $
b1010 "
b1010 !
#110000000000000
b110 $
b1011 "
b1011 !
#120000000000000
b1000 $
b1100 "
b1100 !
#130000000000000
b1010 $
b1101 "
b1101 !
#140000000000000
b1100 $
b1110 "
b1110 !
#150000000000000
b1110 $
b1111 "
b1111 !
#160000000000000
b1111 $
1#
