school/carry_lookahead_adder_4bit.v
module carry_lookahead_adder_4bit(
    input [3:0] A, B,
    input Cin,
    output [3:0] Sum,
    output Cout
);
    wire [3:0] G, P, C;
    assign #1 G = A & B; // Generate
    assign #1 P = A ^ B; // Propagate
    assign C[0] = Cin;
    assign #2 C[1] = G[0] | (P[0] & C[0]);
    assign #2 C[2] = G[1] | (P[1] & G[0]) | (P[1] & P[0] & C[0]);
    assign #2 C[3] = G[2] | (P[2] & G[1]) | (P[2] & P[1] & G[0]) | (P[2] & P[1] & P[0] & C[0]);
    assign #2 Cout = G[3] | (P[3] & G[2]) | (P[3] & P[2] & G[1]) | (P[3] & P[2] & P[1] & G[0]) | (P[3] &
    P[2] & P[1] & P[0] & C[0]);
    assign #1 Sum = P ^ C;
endmodule

school/full_adder.v
module full_adder(
    input a, b, cin,
    output sum, cout
);
    assign #1 sum = a ^ b ^ cin;
    assign #3 cout = (a & b) | (cin & (a ^ b));
endmodule

school/ripple_carry_adder_4bit.v
module ripple_carry_adder_4bit(
    input [3:0] A, B,
    input Cin,
    output [3:0] Sum,
    output Cout
);
    wire [3:0] C;
    full_adder FA0(.a(A[0]), .b(B[0]), .cin(Cin), .sum(Sum[0]), .cout(C[0]));
    full_adder FA1(.a(A[1]), .b(B[1]), .cin(C[0]), .sum(Sum[1]), .cout(C[1]));
    full_adder FA2(.a(A[2]), .b(B[2]), .cin(C[1]), .sum(Sum[2]), .cout(C[2]));
    full_adder FA3(.a(A[3]), .b(B[3]), .cin(C[2]), .sum(Sum[3]), .cout(Cout));
endmodule

school/adder_comparison_tb.v
module adder_comparison_tb;
    reg [3:0] A, B;
    reg Cin;
    wire [3:0] Sum_RCA, Sum_CLA;
    wire Cout_RCA, Cout_CLA;
    
    // Instantiate both adders
    ripple_carry_adder_4bit RCA(
        .A(A), .B(B), .Cin(Cin),
        .Sum(Sum_RCA), .Cout(Cout_RCA)
    ); 
    
    carry_lookahead_adder_4bit CLA(
        .A(A), .B(B), .Cin(Cin),
        .Sum(Sum_CLA), .Cout(Cout_CLA)
    ); 

    initial begin
        // Initialize VCD dump
        $dumpfile("adder_comparison_tb.vcd");
        $dumpvars(0, adder_comparison_tb);
        
        // Test cases
        test_case(9'b000000000);
        test_case(9'b000100100);
        test_case(9'b000000000);
        test_case(9'b001101000);
        test_case(9'b000000000);
        test_case(9'b111100010);
        #20;
        $finish;
    end
    
    task test_case;
        input [8:0] inputs;
        begin
            {A, B, Cin} = inputs;
            #20;
        end
    endtask

endmodule

school/adder_comp.vcd
$date
	Sat Sep 20 16:49:20 2025
$end
$version
	Icarus Verilog
$end
$timescale
	1s
$end
$scope module adder_comparison_tb $end
$var wire 4 ! Sum_RCA [3:0] $end
$var wire 4 " Sum_CLA [3:0] $end
$var wire 1 # Cout_RCA $end
$var wire 1 $ Cout_CLA $end
$var reg 4 % A [3:0] $end
$var reg 4 & B [3:0] $end
$var reg 1 ' Cin $end
$scope module CLA $end
$var wire 4 ( A [3:0] $end
$var wire 4 ) B [3:0] $end
$var wire 1 ' Cin $end
$var wire 1 $ Cout $end
$var wire 4 * G [3:0] $end
$var wire 4 + P [3:0] $end
$var wire 4 , Sum [3:0] $end
$var wire 4 - C [3:0] $end
$upscope $end
$scope module RCA $end
$var wire 4 . A [3:0] $end
$var wire 4 / B [3:0] $end
$var wire 1 ' Cin $end
$var wire 4 0 Sum [3:0] $end
$var wire 1 # Cout $end
$var wire 4 1 C [3:0] $end
$scope module FA0 $end
$var wire 1 2 a $end
$var wire 1 3 b $end
$var wire 1 ' cin $end
$var wire 1 4 cout $end
$var wire 1 5 sum $end
$upscope $end
$scope module FA1 $end
$var wire 1 6 a $end
$var wire 1 7 b $end
$var wire 1 8 cin $end
$var wire 1 9 cout $end
$var wire 1 : sum $end
$upscope $end
$scope module FA2 $end
$var wire 1 ; a $end
$var wire 1 < b $end
$var wire 1 = cin $end
$var wire 1 > cout $end
$var wire 1 ? sum $end
$upscope $end
$scope module FA3 $end
$var wire 1 @ a $end
$var wire 1 A b $end
$var wire 1 B cin $end
$var wire 1 # cout $end
$var wire 1 C sum $end
$upscope $end
$upscope $end
$scope task test_case $end
$var reg 9 D inputs [8:0] $end
$upscope $end
$upscope $end
$enddefinitions $end
$comment Show the parameter values. $end
$dumpall
$end
#0
$dumpvars
b0 D
xC
xB
0A
0@
x?
x>
x=
0<
0;
x:
x9
x8
07
06
x5
x4
03
02
bzxxx 1
bx 0
b0 /
b0 .
bx0 -
bx ,
bx +
bx *
b0 )
b0 (
0'
b0 &
b0 %
x$
x#
bx "
bx !
$end
#1
bx0 !
bx0 0
05
b0 +
b0 *
#2
bx0 "
bx0 ,
#3
08
0=
0B
0$
b0 -
04
09
bz000 1
0>
0#
#4
0:
0?
b0 !
b0 0
0C
b0 "
b0 ,
#20
12
17
b1 %
b1 (
b1 .
b10 &
b10 )
b10 /
b100100 D
#21
15
b11 !
b11 0
1:
b11 +
#22
b11 "
b11 ,
#40
02
07
b0 %
b0 (
b0 .
b0 &
b0 )
b0 /
b0 D
#41
05
b0 !
b0 0
0:
b0 +
#42
b0 "
b0 ,
#60
12
16
1<
b11 %
b11 (
b11 .
b100 &
b100 )
b100 /
b1101000 D
#61
15
1:
b111 !
b111 0
1?
b111 +
#62
b111 "
b111 ,
#80
02
06
0<
b0 %
b0 (
b0 .
b0 &
b0 )
b0 /
b0 D
#81
05
0:
b0 !
b0 0
0?
b0 +
#82
b0 "
b0 ,
#100
12
16
1;
1@
13
b1111 %
b1111 (
b1111 .
b1 &
b1 )
b1 /
b111100010 D
#101
1:
1?
b1110 !
b1110 0
1C
b1 *
b1110 +
#102
b1110 "
b1110 ,
#103
18
1$
b1110 -
bz001 1
14
#104
b1100 !
b1100 0
0:
b0 "
b0 ,
#106
1=
bz011 1
19
#107
b1000 !
b1000 0
0?
#109
1B
bz111 1
1>
#110
b0 !
b0 0
0C
#112
1#
